{
  "metadata": {
    "generated_at": "2026-04-30T21:42:12.233812",
    "total_ideas": 2,
    "categories": {
      "General": 2
    },
    "sources": {
      "telegram": 2
    }
  },
  "ideas": [
    {
      "id": "06a8e6b3",
      "content": "Al loco ese día darle una variante donde le dé una idea ocurrencia sumando un comando o tarea para que haga en cloud code o cree una estrategia en cloud chat web para después crear un un pront para que code trabaje en lo que necesita",
      "categories": [
        "General"
      ],
      "timestamp": "2026-04-30T21:35:43.490367",
      "source": "telegram"
    },
    {
      "id": "cbc8cfe9",
      "content": "RECYCLAR TETRABRICK COMO BLOQUEADOR RFID , EJEMPLO LLAVE DE AUTO",
      "categories": [
        "General"
      ],
      "timestamp": "2026-04-30T20:56:01.146960",
      "source": "telegram"
    }
  ]
}